lua/rock/__init__.py
lua_rock-1.0.0.dist-info/licenses/LICENSE
lua_rock-1.0.0.dist-info/METADATA
lua_rock-1.0.0.dist-info/WHEEL
lua_rock-1.0.0.dist-info/entry_points.txt
lua_rock-1.0.0.dist-info/top_level.txt
lua_rock-1.0.0.dist-info/RECORD
