Metadata-Version: 2.4
Name: lua.rock
Version: 1.0.0
Summary: Generate rock file
Home-page: https://github.com/huakim/python-create-luarock
License: GPLv3
License-File: LICENSE
Requires-Dist: luadata.luatable
Dynamic: home-page
Dynamic: license
Dynamic: license-file
Dynamic: requires-dist
Dynamic: summary
